.gitignore
LICENSE
Makefile
README.md
codemeta.json
requirements.txt
screenshot_index_cards.jpg
screenshot_index_table.jpg
screenshot_page.jpg
screenshot_sparql.jpg
setup.py
codemeta_server/__init__.py
codemeta_server/main.py
codemeta_server.egg-info/PKG-INFO
codemeta_server.egg-info/SOURCES.txt
codemeta_server.egg-info/dependency_links.txt
codemeta_server.egg-info/entry_points.txt
codemeta_server.egg-info/requires.txt
codemeta_server.egg-info/top_level.txt